glcontext/empty.py
glcontext/__init__.py
glcontext/x11.pypy39-pp73-x86-linux-gnu.so
glcontext/egl.pypy39-pp73-x86-linux-gnu.so
glcontext-2.5.0.dist-info/METADATA
glcontext-2.5.0.dist-info/LICENSE
glcontext-2.5.0.dist-info/WHEEL
glcontext-2.5.0.dist-info/RECORD
glcontext-2.5.0.dist-info/top_level.txt
